geo_centroid/__init__.py
geo_centroid/src/__init__.py
geo_centroid/src/centroid_calculator.py
geo_centroid/test/__init__.py
geo_centroid/test/test_centroid_calculator.py
geocentroid/__init__.py
geocentroid/src/__init__.py
geocentroid/src/centroid_calculator.py
geocentroid/test/__init__.py
geocentroid/test/test_centroid_calculator.py
geocentroid-0.0.10.dist-info/METADATA
geocentroid-0.0.10.dist-info/WHEEL
geocentroid-0.0.10.dist-info/top_level.txt
geocentroid-0.0.10.dist-info/RECORD
