Metadata-Version: 2.1
Name: geocentroid
Version: 0.0.10
Summary: A package to calculate the centroid of a list of addresses.
Home-page: https://github.com/aadityayadav/geo-centroid
Author: Aaditya Yadav/ Aditya Swarup
Author-email: aadityayadav2003@gmail.com, adityaswrup78@gmail.com
License: MIT
Classifier: License :: OSI Approved :: MIT License
Classifier: Programming Language :: Python :: 3.5
Classifier: Operating System :: OS Independent
Requires-Python: >=3.5
Requires-Dist: googlemaps >=4.10.0
Provides-Extra: dev
Requires-Dist: pytest >=7.0 ; extra == 'dev'
Requires-Dist: twine >=4.0.2 ; extra == 'dev'
Requires-Dist: python-dotenv >=1.0.0 ; extra == 'dev'
Requires-Dist: wheel >=0.37.0 ; extra == 'dev'
